vscodl/__init__.py
vscodl/constants.py
vscodl/vsco.py
vscodl/vscodl.py
vsco_dl-0.3.4.dist-info/LICENSE
vsco_dl-0.3.4.dist-info/METADATA
vsco_dl-0.3.4.dist-info/WHEEL
vsco_dl-0.3.4.dist-info/entry_points.txt
vsco_dl-0.3.4.dist-info/top_level.txt
vsco_dl-0.3.4.dist-info/RECORD
