Metadata-Version: 2.1
Name: vsco-dl
Version: 0.3.4
Summary: Tool for downloading VSCO user images and journals
Home-page: https://github.com/tecome/vsco-dl
Author: tecome
Author-email: tecome@protonmail.com
License: UNKNOWN
Keywords: vsco dl scrape download image
Platform: UNKNOWN
Classifier: Programming Language :: Python :: 3
Classifier: Operating System :: OS Independent
Requires-Python: >=3.5
License-File: LICENSE
Requires-Dist: tqdm
Requires-Dist: requests
Requires-Dist: beautifulsoup4
